[{"ID":"2","Name":["1","1"],"Password":"12345678"},{"ID":"3","Name":["1","1"],"Password":"12345678"},{"ID":"4","Name":["1","1"],"Password":"12345678"},{"ID":"5","Name":["1","1"],"Password":"12345678"},{"ID":"6","Name":["1","1"],"Password":"12345678"},{"ID":"6","Name":["1","1"],"Password":"12345678"},{"ID":"7","Name":["1","1"],"Password":"12345678"},{"ID":"8","Name":["1","1"],"Password":"12345678"},{"ID":"8","Name":["1","1"],"Password":"12345678"},{"ID":"10","Name":["1","1"],"Password":"12345678"},{"ID":"10","Name":["1","1"],"Password":"12345678"},{"ID":"10","Name":["1","1"],"Password":"12345678"},{"ID":"15","Name":["1","1"],"Password":"12345678"},{"ID":"10","Name":["1","1"],"Password":"12345678"},{"ID":"30","Name":["1","2"],"Password":"12345678"},{"ID":"3","Name":["1","2"],"Password":"12345678"},{"ID":"3","Name":["1","23"],"Password":"12345678"},{"ID":"3","Name":["1","2"],"Password":"12345678"},{"ID":"3","Name":["1","2"],"Password":"12345678"},{"ID":"31","Name":["11","21"],"Password":"123456781"},{"ID":"31","Name":["11","21"],"Password":"123456781"},{"ID":"45245","Name":["55","4545"],"Password":"11111111"},{"ID":"3231","Name":["1","2"],"Password":"11111111"},{"ID":"123123","Name":["1","2"],"Password":"12345678"},{"ID":"31224","Name":["123","123"],"Password":"11111111"},{"ID":"456456345","Name":["456456","45645123.5456"],"Password":"12345678"},{"ID":"12312365","Name":["1","4545"],"Password":"12345678"},{"ID":"123112312345612","Name":["123","12312"],"Password":"12345678"},{"ID":"112255","Name":["123","321"],"Password":"11111111"},{"ID":"4466","Name":["123","456"],"Password":"12345678"},{"ID":"12345678","Name":["132465","123"],"Password":"12345678"},{"ID":"16456453","Name":["123456789","156"],"Password":"12345678"},{"ID":"16456453","Name":["123456789","156"],"Password":"12345678"},{"ID":"112233","Name":["123","312"],"Password":"12345678"},{"ID":"12333124","Name":["123","123"],"Password":"12345678"},{"ID":"12333124454","Name":["123","123"],"Password":"12345678"},{"ID":"123331244549","Name":["123","123"],"Password":"12345678"},{"ID":"1233312445496","Name":["123","123"],"Password":"12345678"},{"ID":"1233312445496","Name":["123","123"],"Password":"12345678"}]